MANIFEST.in
setup.py
getchs/__init__.py
iterminator/__init__.py
iterminator/iterminator.py
iterminator/version.txt
iterminator.egg-info/PKG-INFO
iterminator.egg-info/SOURCES.txt
iterminator.egg-info/dependency_links.txt
iterminator.egg-info/entry_points.txt
iterminator.egg-info/not-zip-safe
iterminator.egg-info/top_level.txt
iterminator/iTerm2-Color-Schemes/.git
iterminator/iTerm2-Color-Schemes/.gitignore
iterminator/iTerm2-Color-Schemes/README.md
iterminator/iTerm2-Color-Schemes/schemes/3024 Day.itermcolors
iterminator/iTerm2-Color-Schemes/schemes/3024 Night.itermcolors
iterminator/iTerm2-Color-Schemes/schemes/AdventureTime.itermcolors
iterminator/iTerm2-Color-Schemes/schemes/Afterglow.itermcolors
iterminator/iTerm2-Color-Schemes/schemes/AlienBlood.itermcolors
iterminator/iTerm2-Color-Schemes/schemes/Argonaut.itermcolors
iterminator/iTerm2-Color-Schemes/schemes/Arthur.itermcolors
iterminator/iTerm2-Color-Schemes/schemes/AtelierSulphurpool.itermcolors
iterminator/iTerm2-Color-Schemes/schemes/Atom.itermcolors
iterminator/iTerm2-Color-Schemes/schemes/AtomOneLight.itermcolors
iterminator/iTerm2-Color-Schemes/schemes/Batman.itermcolors
iterminator/iTerm2-Color-Schemes/schemes/Belafonte Day.itermcolors
iterminator/iTerm2-Color-Schemes/schemes/Belafonte Night.itermcolors
iterminator/iTerm2-Color-Schemes/schemes/BirdsOfParadise.itermcolors
iterminator/iTerm2-Color-Schemes/schemes/Blazer.itermcolors
iterminator/iTerm2-Color-Schemes/schemes/Borland.itermcolors
iterminator/iTerm2-Color-Schemes/schemes/Bright Lights.itermcolors
iterminator/iTerm2-Color-Schemes/schemes/Broadcast.itermcolors
iterminator/iTerm2-Color-Schemes/schemes/Brogrammer.itermcolors
iterminator/iTerm2-Color-Schemes/schemes/C64.itermcolors
iterminator/iTerm2-Color-Schemes/schemes/CLRS.itermcolors
iterminator/iTerm2-Color-Schemes/schemes/Chalk.itermcolors
iterminator/iTerm2-Color-Schemes/schemes/Chalkboard.itermcolors
iterminator/iTerm2-Color-Schemes/schemes/Ciapre.itermcolors
iterminator/iTerm2-Color-Schemes/schemes/Cobalt Neon.itermcolors
iterminator/iTerm2-Color-Schemes/schemes/Cobalt2.itermcolors
iterminator/iTerm2-Color-Schemes/schemes/CrayonPonyFish.itermcolors
