Metadata-Version: 1.0
Name: iterminator
Version: 0.1.9
Summary: Command-line color scheme selector for iTerm2
Home-page: UNKNOWN
Author: Dan Davison
Author-email: dandavison7@gmail.com
License: UNKNOWN
Platform: UNKNOWN
